kerasN/__init__.py
kerasN/activations/__init__.py
kerasN/activations/activations.py
kerasN/activations/__pycache__/__init__.cpython-38.pyc
kerasN/activations/__pycache__/activations.cpython-38.pyc
kerasN/callbacks/__init__.py
kerasN/callbacks/base.py
kerasN/callbacks/early_stopping.py
kerasN/callbacks/model_checkpoint.py
kerasN/datasets/README.md
kerasN/datasets/__init__.py
kerasN/datasets/datasets.py
kerasN/datasets/download_datasets.py
kerasN/datasets/pyodide_datasets.py
kerasN/layers/__init__.py
kerasN/layers/base.py
kerasN/layers/batch_normalization.py
kerasN/layers/conv.py
kerasN/layers/dense.py
kerasN/layers/dropout.py
kerasN/layers/flatten.py
kerasN/layers/input.py
kerasN/layers/pooling.py
kerasN/models/__init__.py
kerasN/models/sequential.py
kerasN/models/pretrained/__init__.py
kerasN/models/pretrained/base.py
kerasN/models/pretrained/mobilenet.py
kerasN/utils/__init__.py
kerasN/utils/conv_utils.py
kerasN/utils/data_loader.py
kerasN/utils/data_utils.py
kerasN/utils/metrics.py
kerasN/utils/preprocessing.py
kerasN/utils/progress.py
kerasN/utils/progress_bar.py
kerasN/utils/transfer.py
kerasN/utils/visualization.py
kerasN/utils/weight_converter.py
kerasN-0.1.1.dist-info/METADATA
kerasN-0.1.1.dist-info/WHEEL
kerasN-0.1.1.dist-info/top_level.txt
kerasN-0.1.1.dist-info/RECORD
