Metadata-Version: 2.2
Name: kerasN
Version: 0.1.1
Summary: A pure Python/NumPy implementation of deep learning framework
Home-page: https://github.com/AshleyLee00/KerasN
Author: Yeseol Lee
Author-email: Yeseol Lee <yebubu00@gmail.com>
Project-URL: Homepage, https://github.com/AshleyLee00/KerasN
Project-URL: Bug Tracker, https://github.com/AshleyLee00/KerasN/issues
Classifier: Programming Language :: Python :: 3
Classifier: License :: OSI Approved :: MIT License
Classifier: Operating System :: OS Independent
Requires-Python: >=3.7
Requires-Dist: numpy>=1.19.2
Requires-Dist: matplotlib>=3.3.2
Requires-Dist: scikit-learn>=0.23.2
Requires-Dist: pandas>=1.2.0
Dynamic: author
Dynamic: home-page
Dynamic: requires-python
